nao_core/__init__.py
nao_core/__init__.py.bak
nao_core/main.py
nao_core/bin/build-info.json
nao_core/bin/nao-chat-server
nao_core/bin/rg
nao_core/bin/fastapi/main.py
nao_core/bin/fastapi/test_main.py
nao_core/bin/migrations-postgres/0000_user_auth_and_chat_tables.sql
nao_core/bin/migrations-postgres/0001_message_feedback.sql
nao_core/bin/migrations-postgres/0002_chat_message_stop_reason_and_error_message.sql
nao_core/bin/migrations-postgres/0003_handle_slack_with_thread.sql
nao_core/bin/migrations-postgres/0004_input_and_output_tokens.sql
nao_core/bin/migrations-postgres/0005_add_project_tables.sql
nao_core/bin/migrations-postgres/0006_llm_model_ids.sql
nao_core/bin/migrations-postgres/0007_chat_message_llm_info.sql
nao_core/bin/migrations-postgres/meta/0000_snapshot.json
nao_core/bin/migrations-postgres/meta/0001_snapshot.json
nao_core/bin/migrations-postgres/meta/0002_snapshot.json
nao_core/bin/migrations-postgres/meta/0003_snapshot.json
nao_core/bin/migrations-postgres/meta/0004_snapshot.json
nao_core/bin/migrations-postgres/meta/0005_snapshot.json
nao_core/bin/migrations-postgres/meta/0006_snapshot.json
nao_core/bin/migrations-postgres/meta/_journal.json
nao_core/bin/migrations-sqlite/0000_user_auth_and_chat_tables.sql
nao_core/bin/migrations-sqlite/0001_message_feedback.sql
nao_core/bin/migrations-sqlite/0002_chat_message_stop_reason_and_error_message.sql
nao_core/bin/migrations-sqlite/0003_handle_slack_with_thread.sql
nao_core/bin/migrations-sqlite/0004_input_and_output_tokens.sql
nao_core/bin/migrations-sqlite/0005_add_project_tables.sql
nao_core/bin/migrations-sqlite/0006_llm_model_ids.sql
nao_core/bin/migrations-sqlite/0007_chat_message_llm_info.sql
nao_core/bin/migrations-sqlite/meta/0000_snapshot.json
nao_core/bin/migrations-sqlite/meta/0001_snapshot.json
nao_core/bin/migrations-sqlite/meta/0002_snapshot.json
nao_core/bin/migrations-sqlite/meta/0003_snapshot.json
nao_core/bin/migrations-sqlite/meta/0004_snapshot.json
nao_core-0.0.38.dist-info/METADATA
nao_core-0.0.38.dist-info/WHEEL
nao_core-0.0.38.dist-info/entry_points.txt
nao_core-0.0.38.dist-info/licenses/LICENSE
nao_core-0.0.38.dist-info/RECORD
