Metadata-Version: 2.4
Name: nao-core
Version: 0.0.38
Summary: nao Core is your analytics context builder with the best chat interface.
Project-URL: Homepage, https://getnao.io
Project-URL: Repository, https://github.com/naolabs/chat
Author: nao Labs
License-Expression: Apache-2.0
License-File: LICENSE
Keywords: ai,analytics,chat
Classifier: Development Status :: 3 - Alpha
Classifier: Environment :: Console
Classifier: Intended Audience :: Developers
Classifier: License :: OSI Approved :: Apache Software License
Classifier: Operating System :: MacOS
Classifier: Programming Language :: Python :: 3
Classifier: Programming Language :: Python :: 3.10
Classifier: Programming Language :: Python :: 3.11
Classifier: Programming Language :: Python :: 3.12
Classifier: Programming Language :: Python :: 3.13
Requires-Python: >=3.10
Requires-Dist: anthropic>=0.76.0
Requires-Dist: apscheduler>=3.10.0
Requires-Dist: cryptography>=46.0.3
Requires-Dist: cyclopts>=4.4.4
Requires-Dist: dotenv>=0.9.9
Requires-Dist: fastapi>=0.128.0
Requires-Dist: ibis-framework[bigquery,databricks,duckdb,postgres,snowflake]>=9.0.0
Requires-Dist: jinja2>=3.1.0
Requires-Dist: notion-client>=2.7.0
Requires-Dist: notion2md>=2.9.0
Requires-Dist: openai>=1.0.0
Requires-Dist: pydantic>=2.10.0
Requires-Dist: pytest>=9.0.2
Requires-Dist: python-dotenv>=1.2.1
Requires-Dist: pyyaml>=6.0.0
Requires-Dist: rich>=14.0.0
Requires-Dist: uvicorn>=0.40.0
